LICENSE
README.md
setup.py
mygame_scraper.egg-info/PKG-INFO
mygame_scraper.egg-info/SOURCES.txt
mygame_scraper.egg-info/dependency_links.txt
mygame_scraper.egg-info/requires.txt
mygame_scraper.egg-info/top_level.txt
pypi_scraper/__init__.py